nipher_src/__init__.py
nipher_src/nipher.py
Nipher-0.1.1b0.dist-info/LICENSE
Nipher-0.1.1b0.dist-info/METADATA
Nipher-0.1.1b0.dist-info/WHEEL
Nipher-0.1.1b0.dist-info/entry_points.txt
Nipher-0.1.1b0.dist-info/top_level.txt
Nipher-0.1.1b0.dist-info/RECORD
